{
  "attributes": [
    {
      "allow_nil?": false,
      "default": "fragment(\"gen_random_uuid()\")",
      "generated?": false,
      "precision": null,
      "primary_key?": true,
      "references": null,
      "scale": null,
      "size": null,
      "source": "id",
      "type": "uuid"
    },
    {
      "allow_nil?": false,
      "default": "nil",
      "generated?": false,
      "precision": null,
      "primary_key?": false,
      "references": null,
      "scale": null,
      "size": null,
      "source": "category",
      "type": "text"
    },
    {
      "allow_nil?": false,
      "default": "nil",
      "generated?": false,
      "precision": null,
      "primary_key?": false,
      "references": null,
      "scale": null,
      "size": null,
      "source": "event_type",
      "type": "text"
    },
    {
      "allow_nil?": true,
      "default": "1",
      "generated?": false,
      "precision": null,
      "primary_key?": false,
      "references": null,
      "scale": null,
      "size": null,
      "source": "severity",
      "type": "bigint"
    },
    {
      "allow_nil?": false,
      "default": "nil",
      "generated?": false,
      "precision": null,
      "primary_key?": false,
      "references": null,
      "scale": null,
      "size": null,
      "source": "message",
      "type": "text"
    },
    {
      "allow_nil?": true,
      "default": "nil",
      "generated?": false,
      "precision": null,
      "primary_key?": false,
      "references": null,
      "scale": null,
      "size": null,
      "source": "details",
      "type": "text"
    },
    {
      "allow_nil?": true,
      "default": "nil",
      "generated?": false,
      "precision": null,
      "primary_key?": false,
      "references": null,
      "scale": null,
      "size": null,
      "source": "source_type",
      "type": "text"
    },
    {
      "allow_nil?": true,
      "default": "nil",
      "generated?": false,
      "precision": null,
      "primary_key?": false,
      "references": null,
      "scale": null,
      "size": null,
      "source": "source_id",
      "type": "text"
    },
    {
      "allow_nil?": true,
      "default": "nil",
      "generated?": false,
      "precision": null,
      "primary_key?": false,
      "references": null,
      "scale": null,
      "size": null,
      "source": "source_name",
      "type": "text"
    },
    {
      "allow_nil?": true,
      "default": "nil",
      "generated?": false,
      "precision": null,
      "primary_key?": false,
      "references": null,
      "scale": null,
      "size": null,
      "source": "target_type",
      "type": "text"
    },
    {
      "allow_nil?": true,
      "default": "nil",
      "generated?": false,
      "precision": null,
      "primary_key?": false,
      "references": null,
      "scale": null,
      "size": null,
      "source": "target_id",
      "type": "text"
    },
    {
      "allow_nil?": true,
      "default": "nil",
      "generated?": false,
      "precision": null,
      "primary_key?": false,
      "references": null,
      "scale": null,
      "size": null,
      "source": "target_name",
      "type": "text"
    },
    {
      "allow_nil?": true,
      "default": "nil",
      "generated?": false,
      "precision": null,
      "primary_key?": false,
      "references": {
        "deferrable": false,
        "destination_attribute": "uid",
        "destination_attribute_default": null,
        "destination_attribute_generated": null,
        "index?": false,
        "match_type": null,
        "match_with": null,
        "multitenancy": {
          "attribute": "tenant_id",
          "global": true,
          "strategy": "attribute"
        },
        "name": "monitoring_events_device_uid_fkey",
        "on_delete": null,
        "on_update": null,
        "primary_key?": true,
        "schema": "public",
        "table": "ocsf_devices"
      },
      "scale": null,
      "size": null,
      "source": "device_uid",
      "type": "text"
    },
    {
      "allow_nil?": true,
      "default": "nil",
      "generated?": false,
      "precision": null,
      "primary_key?": false,
      "references": {
        "deferrable": false,
        "destination_attribute": "uid",
        "destination_attribute_default": null,
        "destination_attribute_generated": null,
        "index?": false,
        "match_type": null,
        "match_with": null,
        "multitenancy": {
          "attribute": "tenant_id",
          "global": true,
          "strategy": "attribute"
        },
        "name": "monitoring_events_agent_uid_fkey",
        "on_delete": null,
        "on_update": null,
        "primary_key?": true,
        "schema": "public",
        "table": "ocsf_agents"
      },
      "scale": null,
      "size": null,
      "source": "agent_uid",
      "type": "text"
    },
    {
      "allow_nil?": true,
      "default": "nil",
      "generated?": false,
      "precision": null,
      "primary_key?": false,
      "references": {
        "deferrable": false,
        "destination_attribute": "id",
        "destination_attribute_default": null,
        "destination_attribute_generated": null,
        "index?": false,
        "match_type": null,
        "match_with": null,
        "multitenancy": {
          "attribute": "tenant_id",
          "global": true,
          "strategy": "attribute"
        },
        "name": "monitoring_events_alert_id_fkey",
        "on_delete": null,
        "on_update": null,
        "primary_key?": true,
        "schema": "public",
        "table": "alerts"
      },
      "scale": null,
      "size": null,
      "source": "alert_id",
      "type": "uuid"
    },
    {
      "allow_nil?": true,
      "default": "%{}",
      "generated?": false,
      "precision": null,
      "primary_key?": false,
      "references": null,
      "scale": null,
      "size": null,
      "source": "metadata",
      "type": "map"
    },
    {
      "allow_nil?": true,
      "default": "[]",
      "generated?": false,
      "precision": null,
      "primary_key?": false,
      "references": null,
      "scale": null,
      "size": null,
      "source": "tags",
      "type": [
        "array",
        "text"
      ]
    },
    {
      "allow_nil?": true,
      "default": "nil",
      "generated?": false,
      "precision": null,
      "primary_key?": false,
      "references": null,
      "scale": null,
      "size": null,
      "source": "actor_type",
      "type": "text"
    },
    {
      "allow_nil?": true,
      "default": "nil",
      "generated?": false,
      "precision": null,
      "primary_key?": false,
      "references": null,
      "scale": null,
      "size": null,
      "source": "actor_id",
      "type": "text"
    },
    {
      "allow_nil?": true,
      "default": "nil",
      "generated?": false,
      "precision": null,
      "primary_key?": false,
      "references": null,
      "scale": null,
      "size": null,
      "source": "actor_name",
      "type": "text"
    },
    {
      "allow_nil?": true,
      "default": "nil",
      "generated?": false,
      "precision": null,
      "primary_key?": false,
      "references": null,
      "scale": null,
      "size": null,
      "source": "client_ip",
      "type": "text"
    },
    {
      "allow_nil?": false,
      "default": "nil",
      "generated?": false,
      "precision": null,
      "primary_key?": false,
      "references": null,
      "scale": null,
      "size": null,
      "source": "occurred_at",
      "type": "utc_datetime"
    },
    {
      "allow_nil?": false,
      "default": "nil",
      "generated?": false,
      "precision": null,
      "primary_key?": false,
      "references": null,
      "scale": null,
      "size": null,
      "source": "tenant_id",
      "type": "uuid"
    },
    {
      "allow_nil?": false,
      "default": "fragment(\"(now() AT TIME ZONE 'utc')\")",
      "generated?": false,
      "precision": null,
      "primary_key?": false,
      "references": null,
      "scale": null,
      "size": null,
      "source": "created_at",
      "type": "utc_datetime_usec"
    }
  ],
  "base_filter": null,
  "check_constraints": [],
  "custom_indexes": [],
  "custom_statements": [],
  "has_create_action": true,
  "hash": "D387B7F715E2D3C77E3F1368AE9DF942E238A4751C0EC034EF84232F7BB7044D",
  "identities": [],
  "multitenancy": {
    "attribute": "tenant_id",
    "global": true,
    "strategy": "attribute"
  },
  "repo": "Elixir.ServiceRadarWebNG.Repo",
  "schema": null,
  "table": "monitoring_events"
}